aws_recommendation_a14/__init__.py
aws_recommendation_a14/cloudwatch.py
aws_recommendation_a14/cost_estimations.py
aws_recommendation_a14/dynamodb.py
aws_recommendation_a14/ebs.py
aws_recommendation_a14/ec2.py
aws_recommendation_a14/elb.py
aws_recommendation_a14/kms.py
aws_recommendation_a14/rds.py
aws_recommendation_a14/recommendation.py
aws_recommendation_a14/redshift.py
aws_recommendation_a14/s3.py
aws_recommendation_a14/truted_advisor.py
aws_recommendation_a14/utils.py
aws_recommendation_a14-0.0.26.dist-info/LICENCE
aws_recommendation_a14-0.0.26.dist-info/METADATA
aws_recommendation_a14-0.0.26.dist-info/WHEEL
aws_recommendation_a14-0.0.26.dist-info/top_level.txt
aws_recommendation_a14-0.0.26.dist-info/RECORD
